kafka_robot/__init__.py
kafka_robot/kafka_client.py
kafka_robot/t1.py
kafka_robot/test.py
kafka_robot-2.3.2.data/data/LICENSE
kafka_robot-2.3.2.dist-info/LICENSE
kafka_robot-2.3.2.dist-info/METADATA
kafka_robot-2.3.2.dist-info/WHEEL
kafka_robot-2.3.2.dist-info/top_level.txt
kafka_robot-2.3.2.dist-info/RECORD
