Metadata-Version: 2.1
Name: kafka-robot
Version: 2.3.2
Summary: Package for recieving messages from Kafka in Robot Framework.
Home-page: UNKNOWN
License: 2.3.2
Platform: UNKNOWN
Classifier: Programming Language :: Python :: 3
Classifier: Operating System :: OS Independent
Requires-Python: >=3.6
Requires-Dist: six
Requires-Dist: robotframework (>=3.1.2)
Requires-Dist: kafka-python (>=2.0.1)
